{
	"dialogue": [
		{
			"expression": "talk",
			"text": "...y por eso AMLO es el mejor presidente que\\nha tenido Mexico.",
			"boxState": "normal",
			"portrait": "jp",
			"speed": 0.025
		},
		{
			"expression": "talk",
			"text": "todo bien juan pablo pero yo cuando pregunte",
			"boxState": "normal",
			"portrait": "cesar",
			"speed": 0.05
		},
		{
			"expression": "talk",
			"text": "solo estabamos hablando de la inmortalidad del cangrejo y de repente te pusiste a darme un sermon de como amlo es el mejor ser humano",
			"boxState": "normal",
			"portrait": "cesar",
			"speed": 0.05
		},
		{
			"expression": "talk",
			"text": "De que estan hablando?",
			"boxState": "normal",
			"portrait": "bf",
			"speed": 0.05
		},
		{
			"expression": "talk",
			"text": "De mi queridisimo papucho sensual Andres Manuel Lopez Obrador.",
			"boxState": "normal",
			"portrait": "jp",
			"speed": 0.025
		},
		{
			"expression": "talk",
			"text": "No me digas que eres uno de esos idiotas que no aprecia a AMLO como nuestro \\nsalvador?",
			"boxState": "normal",
			"portrait": "jp",
			"speed": 0.025
		},
		{
			"expression": "talk",
			"text": "Pues AMLO no ha sido tan prometedor como parecia las ultimas decadas que rogo ser presidente.",
			"boxState": "normal",
			"portrait": "bf",
			"speed": 0.05
		},
		{
			"expression": "talk",
			"text": " ",
			"boxState": "normal",
			"portrait": "jp",
			"speed": 0
		},
		{
			"expression": "furious",
			"text": "Repite eso.",
			"boxState": "normal",
			"portrait": "jp",
			"speed": 0.1
		},
		{
			"expression": "talk",
			"text": "Pues AMLO no ha sido tan prometedor como parecia las ultimas decadas que rogo ser presidente.",
			"boxState": "normal",
			"sound": "",
			"speed": 0.00500000000000001,
			"portrait": "TsuyAr"
		},
		{
			"expression": "talk",
			"text": "Dije que-",
			"boxState": "normal",
			"portrait": "bf",
			"speed": 0.05
		},
		{
			"expression": "furious",
			"text": "TE ESCUCHE BIEN LA PRIMERA VEZ!",
			"boxState": "angry",
			"portrait": "jp",
			"speed": 0.015
		},
		{
			"expression": "talk",
			"text": "NADIE LLAMA A MI ANDRES MANUEL LOPEZ OBRADOR UN ROGADOR!",
			"boxState": "angry",
			"portrait": "jp",
			"speed": 0.015
		},
		{
			"expression": "talk",
			"text": "El Peje es bien carismatico, cosa que los demas presidentes no han sido desde la decada de la mama de tu mama de tu mama!",
			"boxState": "angry",
			"portrait": "jp",
			"speed": 0.025
		},
		{
			"expression": "talk",
			"text": "A  S  F! ",
			"boxState": "angry",
			"portrait": "jp",
			"speed": 0.075
		},
		{
			"expression": "talk",
			"text": "A  S  F!",
			"boxState": "angry",
			"portrait": "jp",
			"speed": 0.085
		},
		{
			"expression": "talk",
			"text": "A  S  F!",
			"boxState": "angry",
			"portrait": "jp",
			"speed": 0.095
		},
		{
			"expression": "talk",
			"text": "Pues es que si es un rogador...",
			"boxState": "normal",
			"portrait": "bf",
			"speed": 0.05
		},
		{
			"expression": "wtf",
			"text": "La palabra ''rogador'' existe?",
			"boxState": "normal",
			"sound": "",
			"speed": 0.03,
			"portrait": "TsuyAr"
		},
		{
			"expression": "talk",
			"text": "no c",
			"boxState": "normal",
			"sound": "",
			"speed": 0.04,
			"portrait": "Cesar"
		},
		{
			"expression": "unamused",
			"text": "Muchas gracias",
			"boxState": "normal",
			"sound": "",
			"speed": 0.03,
			"portrait": "TsuyAr"
		},
		{
			"expression": "talk",
			"text": "de nada tuyasr",
			"boxState": "normal",
			"sound": "",
			"speed": 0.035,
			"portrait": "Cesar"
		},
		{
			"expression": "talk",
			"text": "No tienes ningun derecho a insultarlo de tal forma.",
			"boxState": "normal",
			"speed": 0.035,
			"portrait": "jp"
		},
		{
			"expression": "talk",
			"text": "ya volvi de cagar",
			"boxState": "normal",
			"speed": 0.05,
			"portrait": "bule"
		},
		{
			"expression": "talk",
			"text": "a ver juan pablo ganale",
			"boxState": "normal",
			"speed": 0.035,
			"portrait": "cesar"
		},
		{
			"expression": "talk",
			"text": "Es justo lo que tenia planeado.",
			"boxState": "normal",
			"speed": 0.04,
			"portrait": "jp"
		},
		{
			"expression": "talk",
			"text": "hijole que ya valiste",
			"boxState": "normal",
			"speed": 0.05,
			"portrait": "cesar"
		},
		{
			"expression": "talk",
			"text": "Esta follada de ano la tengo que subir a\\nXVideos",
			"boxState": "normal",
			"sound": "",
			"speed": 0.03,
			"portrait": "TsuyAr"
		},
		{
			"expression": "talk",
			"text": "delicioso",
			"boxState": "normal",
			"sound": "",
			"speed": 0.055,
			"portrait": "brown"
		},
		{
			"expression": "unamused",
			"text": "ya borra tu cuenta brownish",
			"boxState": "normal",
			"sound": "",
			"speed": 0.05,
			"portrait": "TsuyAr"
		},
		{
			"expression": "angry",
			"text": "cuando eute sech y el pepe se casen",
			"boxState": "normal",
			"sound": "",
			"speed": 0.02,
			"portrait": "Brown"
		},
		{
			"expression": "angry",
			"text": "y hagan una sex tape",
			"boxState": "normal",
			"sound": "",
			"speed": 0.02,
			"portrait": "brown"
		},
		{
			"expression": "talk",
			"text": "o sea",
			"boxState": "normal",
			"sound": "",
			"speed": 0.04,
			"portrait": "Isaac"
		},
		{
			"expression": "talk",
			"text": "de que",
			"boxState": "normal",
			"sound": "",
			"speed": 0.04,
			"portrait": "isaac"
		},
		{
			"expression": "talk",
			"text": "nunca",
			"boxState": "normal",
			"sound": "",
			"speed": 0.04,
			"portrait": "isaac"
		},
		{
			"expression": "talk",
			"text": "Cuando empieza?",
			"boxState": "normal",
			"sound": "",
			"speed": 0.05,
			"portrait": "bf"
		},
		{
			"expression": "talk",
			"text": "ya",
			"boxState": "normal",
			"sound": "",
			"speed": 0.025,
			"portrait": "jp"
		},
		{
			"sound": "",
			"speed": 0.03,
			"portrait": "TsuyAr",
			"boxState": "normal",
			"expression": "talk",
			"text": "Que bueno que esto solo va a empezar sin preguntarnos porque el yolotroll sabe de la existencia de AMLO"
		}
	]
}